mul/__init__.py
mul/__main__.py
mul/ast.py
mul/interpretation/__init__.py
mul/interpretation/activation_record.py
mul/interpretation/interpreter.py
mul/interpretation/print.py
mul/interpretation/symbol_table.py
mul/interpretation/visitor.py
mul/lexer.py
mul/lib.py
mul/lookahead.py
mul/parser.py
mul/tokens.py
std/lib.mul
mul-0.2.0.dist-info/entry_points.txt
mul-0.2.0.dist-info/WHEEL
mul-0.2.0.dist-info/METADATA
mul-0.2.0.dist-info/RECORD
