Metadata-Version: 2.1
Name: mul
Version: 0.2.0
Summary: mul · My Useless Language, a simple interpreted programming language
Home-page: https://github.com/mattmezza/mul
License: MIT
Keywords: programming-language,language,interpreted
Author: Matteo Merola
Author-email: mattmezza@gmail.com
Requires-Python: >=3.11,<4.0
Classifier: Development Status :: 3 - Alpha
Classifier: Intended Audience :: Developers
Classifier: Intended Audience :: Education
Classifier: License :: OSI Approved :: MIT License
Classifier: Operating System :: MacOS
Classifier: Programming Language :: Python :: 3
Classifier: Programming Language :: Python :: 3.11
Classifier: Programming Language :: Python :: 3.11
Classifier: Topic :: Education
Project-URL: Bug Tracker, https://github.com/mattmezza/poetry/issues
Project-URL: Documentation, https://github.com/mattmezza/mul/blob/main/readme.md
Project-URL: Repository, https://github.com/mattmezza/mul
